{
  "id": "4765_maria_teresa_sanchis_iserte_o_yserte",
  "source_id": "4765",
  "row_ref": "4765. María Teresa Sanchís Iserte [o Yserte]",
  "name": "María Teresa Sanchís Iserte [o Yserte]",
  "gender": "female",
  "birth": {
    "date": "1793-07-22",
    "place": "la Ràpita"
  },
  "death": {
    "date": null,
    "place": null
  },
  "status": {
    "alive": null
  },
  "location": {
    "address": "",
    "lat": null,
    "lng": null
  },
  "family": {
    "parents": [
      "4824_blas_sanches_ximenes"
    ],
    "father": "4824_blas_sanches_ximenes",
    "mother": null,
    "spouse": [
      "175_tomas_arbo_ingles"
    ],
    "children": [],
    "grandparents": {
      "paternal_grandfather": null,
      "paternal_grandmother": null,
      "maternal_grandfather": null,
      "maternal_grandmother": null
    },
    "godparents": {
      "godfather": "5124_blas_silvestre_moreno",
      "godmother": null
    }
  },
  "relations_detail": {
    "parents_names": [
      "Blas Sanches Ximenes",
      "Manuela Yserte"
    ],
    "father_name": "Blas Sanchís Ximenes",
    "mother_name": "Manuela Yserte",
    "spouse_names": [
      "Tomas Arbó Inglés"
    ],
    "children_names": [],
    "grandparents_names": {
      "paternal_grandfather": "",
      "paternal_grandmother": "",
      "maternal_grandfather": "",
      "maternal_grandmother": ""
    },
    "godparents_names": {
      "godfather": "Blas Silvestre Moreno",
      "godmother": null
    }
  },
  "occupation": {
    "title": null
  },
  "education": [],
  "contact": {},
  "photo": "",
  "notes": "Naixement: el 22 de juliol de 1793 a la Ràpita.\n\nPadrins: Blas Silvestre Moreno i Teresa Temprado.\n\nCasament: el 4 de març de 1815 amb Tomás Arbó Inglés de Benicarló [1793].\n\nFills: Juan [1816], Josefa [1820], Peregrín [1824], José [1827], Ramón Tomás [1830] i Felix [1833].",
  "genogram": {
    "nodes": [],
    "links": []
  }
}