{
  "id": "4838_pedro_sancho_adell",
  "source_id": "4838",
  "row_ref": "4838. Pedro Sancho Adell",
  "name": "Pedro Sancho Adell",
  "gender": "male",
  "birth": {
    "date": "1838-01-06",
    "place": "la Ràpita"
  },
  "death": {
    "date": "1838-01-09",
    "place": "la Ràpita"
  },
  "status": {
    "alive": false
  },
  "location": {
    "address": "",
    "lat": null,
    "lng": null
  },
  "family": {
    "parents": [
      "4902_miguel_sancho_matamoros",
      "35_rosa_adell_tallada"
    ],
    "father": "4902_miguel_sancho_matamoros",
    "mother": "35_rosa_adell_tallada",
    "spouse": [],
    "children": [],
    "grandparents": {
      "paternal_grandfather": null,
      "paternal_grandmother": null,
      "maternal_grandfather": null,
      "maternal_grandmother": null
    },
    "godparents": {
      "godfather": null,
      "godmother": null
    }
  },
  "relations_detail": {
    "parents_names": [
      "Miguel Sancho Matamoros",
      "Rosa Adell Tallada"
    ],
    "father_name": "Miguel Sancho Matamoros",
    "mother_name": "Rosa Adell",
    "spouse_names": [],
    "children_names": [],
    "grandparents_names": {
      "paternal_grandfather": "",
      "paternal_grandmother": "",
      "maternal_grandfather": "",
      "maternal_grandmother": ""
    },
    "godparents_names": {
      "godfather": null,
      "godmother": null
    }
  },
  "occupation": {
    "title": null
  },
  "education": [],
  "contact": {},
  "photo": "",
  "notes": "Naixement: el 6 de gener de 1838 a la Ràpita.\n\nDefunció: el 9 de gener de 1838 a la Ràpita. Va morir als 3 dies.",
  "genogram": {
    "nodes": [],
    "links": []
  }
}