{
  "id": "30_juan_bautista_adell_miralles",
  "source_id": "30",
  "row_ref": "30",
  "name": "Juan Bautista Adell Miralles",
  "gender": "male",
  "birth": {
    "date": "1806-01-01",
    "place": "Vinaròs"
  },
  "death": {
    "date": "1809-03-27",
    "place": "la Ràpita"
  },
  "status": {
    "alive": false
  },
  "location": {
    "address": "",
    "lat": null,
    "lng": null
  },
  "family": {
    "parents": [],
    "spouse": [],
    "children": []
  },
  "relations_detail": {
    "parents_names": [
      "Pascual Adell",
      "Mariana Miralles"
    ],
    "spouse_names": [],
    "children_names": []
  },
  "occupation": {
    "title": null
  },
  "education": [],
  "contact": {},
  "photo": "",
  "notes": "Naixement:  [aprox. 1806].\n\nDefunció: el 27 de març de 1809 a la Ràpita. Va morir als 3 anys i 6 mesos \"por casualidad en San Carlos\".",
  "genogram": {
    "nodes": [],
    "links": []
  }
}