{
  "id": "3759_francisca_ortiz_albaran",
  "source_id": "3759",
  "row_ref": "3759. Francisca Ortíz Albarán",
  "name": "Francisca Ortíz Albarán",
  "gender": "female",
  "birth": {
    "date": "1767-01-01",
    "place": "Amposta"
  },
  "death": {
    "date": null,
    "place": null
  },
  "status": {
    "alive": null
  },
  "location": {
    "address": "",
    "lat": null,
    "lng": null
  },
  "family": {
    "parents": [],
    "father": null,
    "mother": null,
    "spouse": [],
    "children": [],
    "grandparents": {
      "paternal_grandfather": null,
      "paternal_grandmother": null,
      "maternal_grandfather": null,
      "maternal_grandmother": null
    },
    "godparents": {
      "godfather": null,
      "godmother": null
    }
  },
  "relations_detail": {
    "parents_names": [],
    "father_name": null,
    "mother_name": null,
    "spouse_names": [],
    "children_names": [],
    "grandparents_names": {
      "paternal_grandfather": "",
      "paternal_grandmother": "",
      "maternal_grandfather": "",
      "maternal_grandmother": ""
    },
    "godparents_names": {
      "godfather": null,
      "godmother": null
    }
  },
  "occupation": {
    "title": null
  },
  "education": [],
  "contact": {},
  "photo": "",
  "notes": "Naixement: a Amposta [aprox. 1767].\n\nCasament: amb Don Luís Guindolain Oliver de Flix [1762].\n\nFills: María Theresa [1805].",
  "genogram": {
    "nodes": [],
    "links": []
  }
}