{
  "id": "4279_manuel_reverte_izquierdo",
  "source_id": "4279",
  "row_ref": "4279. Manuel Reverté Izquierdo",
  "name": "Manuel Reverté Izquierdo",
  "gender": "male",
  "birth": {
    "date": "1821-05-21",
    "place": "la Ràpita"
  },
  "death": {
    "date": null,
    "place": null
  },
  "status": {
    "alive": null
  },
  "location": {
    "address": "",
    "lat": null,
    "lng": null
  },
  "family": {
    "parents": [
      "4259_francisco_reverter_forner",
      "2834_josefa_izquierdo_caldero"
    ],
    "father": "4259_francisco_reverter_forner",
    "mother": "2834_josefa_izquierdo_caldero",
    "spouse": [
      "2440_agustina_gasparin_moya"
    ],
    "children": [],
    "grandparents": {
      "paternal_grandfather": null,
      "paternal_grandmother": null,
      "maternal_grandfather": null,
      "maternal_grandmother": null
    },
    "godparents": {
      "godfather": null,
      "godmother": null
    }
  },
  "relations_detail": {
    "parents_names": [
      "Francisco Reverter Forner",
      "Josefa Izquierdo Calderó"
    ],
    "father_name": "Francisco Reverter Forner",
    "mother_name": "Josefa Izquierdo Calderó",
    "spouse_names": [
      "Agustina Gasparín Moya"
    ],
    "children_names": [],
    "grandparents_names": {
      "paternal_grandfather": "",
      "paternal_grandmother": "",
      "maternal_grandfather": "",
      "maternal_grandmother": ""
    },
    "godparents_names": {
      "godfather": "Josef Reverter",
      "godmother": null
    }
  },
  "occupation": {
    "title": "Pagès"
  },
  "education": [],
  "contact": {},
  "photo": "",
  "notes": "Naixement: el 21 de maig de 1821 a la Ràpita.\n\nPadrins: José Reverter i María Forner.\n\nProfessió: pagès.\n\nCasament: el 6 de maig de 1848 amb Agustina Gasparín Moya de la Ràpita [1823].\n\nFills: Pedro [1856] i Lorenzo [1860].",
  "genogram": {
    "nodes": [],
    "links": []
  }
}