{
  "id": "manuel_arbo_romeu_18801216",
  "source_id": null,
  "name": "Manuel Arbó Romeu",
  "gender": "male",
  "birth": {
    "date": "1880-12-16",
    "place": null
  },
  "death": {
    "date": null,
    "place": null
  },
  "age": null,
  "status": {
    "alive": false
  },
  "location": {
    "address": null,
    "lat": null,
    "lng": null
  },
  "family": {
    "parents": [],
    "spouse": [],
    "children": []
  },
  "relations_detail": {
    "parents_names": [],
    "spouse_names": [],
    "children_names": []
  },
  "occupation": {
    "title": null,
    "company": null
  },
  "education": [],
  "contact": {
    "phone": null,
    "email": null
  },
  "photo": null,
  "notes": "Naixement: el 16 de desembre de 1880 a la Ràpita. El pare es mariner. Al registre civil sembla que hi ha un error: consta com Albiol Romero.",
  "genogram": {
    "nodes": [],
    "links": []
  }
}